{
  "fecha": "2026-07-03",
  "app": "NexoClx 061",
  "rama": "main",
  "commit_inicial": "4c012bd",
  "commit_final": null,
  "tema_creado": "HTA",
  "archivos_modificados": [
    "src/data/placeholders.js",
    "src/screens/ProtocolDetail.jsx",
    "src/styles/index.css",
    "reports/hta-report.json"
  ],
  "fuentes_usadas": [
    "ESC 2024 Guidelines for the management of elevated blood pressure and hypertension",
    "European Society of Hypertension 2023 Guidelines for the management of arterial hypertension",
    "NICE NG136 Hypertension in adults: diagnosis and management",
    "Peacock WF et al. Treatment of hypertensive emergencies. Ann Transl Med. 2017",
    "AHA Systems of Care for ST-Segment-Elevation Myocardial Infarction. Circulation 2021",
    "ACC/AHA 2022 Guideline for the Diagnosis and Management of Aortic Disease"
  ],
  "fuente_por_bloque_clinico": {
    "ABCDE_y_dano_agudo": ["ESC 2024", "ESH 2023"],
    "SCA_codigo_IAM": ["AHA STEMI systems of care 2021"],
    "sindrome_aortico_agudo": ["ACC/AHA 2022 Aortic Disease"],
    "prealerta_hospital_util": ["AHA STEMI systems of care 2021", "ACC/AHA 2022 Aortic Disease", "ESC 2024"],
    "tratamiento_intravenoso_protocolizado": ["Peacock WF et al. 2017"]
  },
  "fuente_por_tratamiento_dosis": {
    "soporte_ABCDE_oxigeno_si_hipoxemia": "ESC 2024 / ESH 2023",
    "labetalol_IV_0_3_1_mg_kg_max_20_mg_y_perf_0_4_1_mg_kg_h": "Peacock WF et al. 2017"
  },
  "dosis_anadidas": [
    "labetalol intravenoso bolo 0,3-1 mg/kg maximo inicial 20 mg y perfusion 0,4-1 mg/kg/h solo si protocolo/direccion medica lo contempla"
  ],
  "escalones_terapeuticos_anadidos": [
    "Soporte ABCDE y traslado",
    "Tratamiento intravenoso solo protocolizado y monitorizado",
    "Transferencia estructurada al receptor"
  ],
  "tratamientos_coadyuvantes_anadidos": [
    "monitorizacion",
    "ECG si dolor toracico/disnea o sospecha de SCA",
    "oxigeno si hipoxemia",
    "prealerta y hospital util"
  ],
  "contenido_omitido_por_falta_de_fuente": [
    "Tratamiento cronico ambulatorio en 061",
    "Dosis de farmacos prehospitalarios sin respaldo de protocolo territorial publicado",
    "Objetivos tensionales especificos no adaptados a direccion medica local"
  ],
  "calculadoras_nuevas": false,
  "formulas_modificadas": false,
  "build": "pass",
  "errores_consola": [],
  "overflow_horizontal": false,
  "colores_base_modificados": false,
  "navegacion_global_modificada": false,
  "vercel_tocado": false,
  "riesgos_pendientes": [
    "Validar con direccion medica local cualquier uso prehospitalario de intravenosos"
  ]
}
